tickvault_python_api-1.2.5.data/data/LICENSE.txt
tickvault_python_api-1.2.5.dist-info/DESCRIPTION.rst
tickvault_python_api-1.2.5.dist-info/METADATA
tickvault_python_api-1.2.5.dist-info/RECORD
tickvault_python_api-1.2.5.dist-info/WHEEL
tickvault_python_api-1.2.5.dist-info/metadata.json
tickvault_python_api-1.2.5.dist-info/top_level.txt
tickvault_python_api-1.2.5.dist-info/zip-safe
tickvaultpythonapi/__init__.py
tickvaultpythonapi/client.py
tickvaultpythonapi/cmedatamineclient.py
tickvaultpythonapi/itsclient.py
tickvaultpythonapi/nasdaqcxclient.py
tickvaultpythonapi/trclient.py
tickvaultpythonapi/auth/__init__.py
tickvaultpythonapi/auth/auth.py
tickvaultpythonapi/parsing/__init__.py
tickvaultpythonapi/parsing/operation.py
tickvaultpythonapi/parsing/parse.py
tickvaultpythonapi/parsing/predicate.py
