Metadata-Version: 2.0
Name: tickvault-python-api
Version: 1.2.5
Summary: TickVault Python Query API
Home-page: https://github.com/ticksmith/tickvault-python-api
Author: TickSmith Corp.
Author-email: support@ticksmith.com
License: MIT
Keywords: tickvault python api client
Platform: any
Classifier: Development Status :: 4 - Beta
Classifier: Environment :: Console
Classifier: Intended Audience :: Developers
Classifier: Intended Audience :: Financial and Insurance Industry
Classifier: License :: OSI Approved :: MIT License
Classifier: Natural Language :: English
Classifier: Operating System :: OS Independent
Classifier: Programming Language :: Python :: 3
Classifier: Programming Language :: Python :: 3.4
Classifier: Programming Language :: Python :: 3.5
Classifier: Programming Language :: Python :: 3.6
Classifier: Topic :: Software Development
Classifier: Topic :: Software Development :: Libraries
Requires-Dist: numpy
Requires-Dist: pandas
Requires-Dist: pyparsing
Requires-Dist: requests
Requires-Dist: ujson
